kindeditor/__init__.py
kindeditor/__version__.py
kindeditor/admin.py
kindeditor/apps.py
kindeditor/fields.py
kindeditor/models.py
kindeditor/urls.py
kindeditor/views.py
kindeditor/widgets.py
kindeditor/static/kindeditor/config.js
kindeditor/static/kindeditor/config.min.js
kindeditor/static/kindeditor/kindeditor-all.js
kindeditor/static/kindeditor/kindeditor-all.min.js
kindeditor/static/kindeditor/lang/ar.js
kindeditor/static/kindeditor/lang/en.js
kindeditor/static/kindeditor/lang/ko.js
kindeditor/static/kindeditor/lang/ru.js
kindeditor/static/kindeditor/lang/zh-CN.js
kindeditor/static/kindeditor/lang/zh-CN.min.js
kindeditor/static/kindeditor/lang/zh-TW.js
kindeditor/static/kindeditor/plugins/anchor/anchor.js
kindeditor/static/kindeditor/plugins/autoheight/autoheight.js
kindeditor/static/kindeditor/plugins/baidumap/baidumap.js
kindeditor/static/kindeditor/plugins/baidumap/index.html
kindeditor/static/kindeditor/plugins/baidumap/map.html
kindeditor/static/kindeditor/plugins/clearhtml/clearhtml.js
kindeditor/static/kindeditor/plugins/code/code.js
kindeditor/static/kindeditor/plugins/code/prettify.css
kindeditor/static/kindeditor/plugins/code/prettify.js
kindeditor/static/kindeditor/plugins/code/prettify.min.css
kindeditor/static/kindeditor/plugins/emoticons/emoticons.js
kindeditor/static/kindeditor/plugins/emoticons/images/0.gif
kindeditor/static/kindeditor/plugins/emoticons/images/1.gif
kindeditor/static/kindeditor/plugins/emoticons/images/10.gif
kindeditor/static/kindeditor/plugins/emoticons/images/100.gif
kindeditor/static/kindeditor/plugins/emoticons/images/101.gif
kindeditor/static/kindeditor/plugins/emoticons/images/102.gif
kindeditor/static/kindeditor/plugins/emoticons/images/103.gif
kindeditor/static/kindeditor/plugins/emoticons/images/104.gif
kindeditor/static/kindeditor/plugins/emoticons/images/105.gif
kindeditor/static/kindeditor/plugins/emoticons/images/106.gif
kindeditor/static/kindeditor/plugins/emoticons/images/107.gif
django_kindeditor-0.3.0.dist-info/LICENSE
django_kindeditor-0.3.0.dist-info/METADATA
django_kindeditor-0.3.0.dist-info/WHEEL
django_kindeditor-0.3.0.dist-info/top_level.txt
django_kindeditor-0.3.0.dist-info/RECORD
