Metadata-Version: 2.1
Name: django-kindeditor
Version: 0.3.0
Summary: Django admin KindEditor integration.
Home-page: https://github.com/waketzheng/django-kindeditor
Author: Waket Zheng
Author-email: waketzheng@gmail.com
License: MIT
Platform: UNKNOWN
Classifier: Development Status :: 3 - Alpha
Classifier: Environment :: Web Environment
Classifier: Framework :: Django
Classifier: Framework :: Django :: 2.0
Classifier: Framework :: Django :: 2.1
Classifier: Framework :: Django :: 2.2
Classifier: Intended Audience :: Developers
Classifier: License :: OSI Approved :: MIT License
Classifier: Operating System :: OS Independent
Classifier: Programming Language :: Python
Classifier: Programming Language :: Python :: 3.6
Classifier: Programming Language :: Python :: 3.7
Classifier: Topic :: Internet :: WWW/HTTP
Requires-Python: >=3.6
Requires-Dist: django (>=2.0)
Requires-Dist: pillow (>=5.3)
